{
  "appInfo" : {
    "build" : "203.7148.57",
    "buildDate" : "Tue, 26 Jan 2021 03:24:13 +0100",
    "productCode" : "IC",
    "generated" : "Tue, 9 Mar 2021 20:29:08 +0100",
    "os" : "Linux 5.8.0-44-generic",
    "runtime" : "JetBrains s.r.o. 11.0.9.1 11.0.9.1+11-b1145.77"
  },
  "runtimeInfo" : {
    "maxMemory" : 536870912,
    "numberOfProcessors" : 24,
    "maxNumberOfIndexingThreads" : 4,
    "maxSizeOfFileForIntelliSense" : 2560000,
    "maxSizeOfFileForContentLoading" : 20971520
  },
  "projectIndexingHistory" : {
    "projectName" : "Demo",
    "numberOfFileProviders" : 7,
    "totalNumberOfFiles" : 246,
    "totalNumberOfUpToDateFiles" : 26,
    "times" : {
      "totalUpdatingTime" : "1 s 95 ms",
      "indexingTime" : "808 ms",
      "pushPropertiesTime" : "17 ms",
      "updatingStart" : "Tue, 9 Mar 2021 20:29:07 +0100",
      "updatingEnd" : "Tue, 9 Mar 2021 20:29:08 +0100",
      "wasInterrupted" : false
    },
    "numberOfIndexingThreads" : 4,
    "totalStatsPerFileType" : [ {
      "fileType" : "XML",
      "partOfTotalIndexingTime" : "52.0%",
      "partOfTotalContentLoadingTime" : "76.6%",
      "totalNumberOfFiles" : 21,
      "totalFilesSize" : "1.06 MB",
      "indexingSpeed" : "1.18 MB/s",
      "biggestContributors" : [ {
        "providerName" : "com.intellij.javaee.ExternalResourcesRootsProvider@4ec914be",
        "numberOfFiles" : 21,
        "totalFilesSize" : "1.06 MB",
        "partOfTotalIndexingTimeOfThisFileType" : "100.0%"
      } ]
    }, {
      "fileType" : "DTD",
      "partOfTotalIndexingTime" : "27.9%",
      "partOfTotalContentLoadingTime" : "14.7%",
      "totalNumberOfFiles" : 62,
      "totalFilesSize" : "601.85 kB",
      "indexingSpeed" : "1.24 MB/s",
      "biggestContributors" : [ {
        "providerName" : "com.intellij.javaee.ExternalResourcesRootsProvider@4ec914be",
        "numberOfFiles" : 62,
        "totalFilesSize" : "601.85 kB",
        "partOfTotalIndexingTimeOfThisFileType" : "100.0%"
      } ]
    }, {
      "fileType" : "RNG Compact",
      "partOfTotalIndexingTime" : "11.4%",
      "partOfTotalContentLoadingTime" : "7.7%",
      "totalNumberOfFiles" : 122,
      "totalFilesSize" : "461.81 kB",
      "indexingSpeed" : "2.33 MB/s",
      "biggestContributors" : [ {
        "providerName" : "com.intellij.javaee.ExternalResourcesRootsProvider@4ec914be",
        "numberOfFiles" : 122,
        "totalFilesSize" : "461.81 kB",
        "partOfTotalIndexingTimeOfThisFileType" : "100.0%"
      } ]
    }, {
      "fileType" : "JAVA",
      "partOfTotalIndexingTime" : "6.9%",
      "partOfTotalContentLoadingTime" : "< 1%",
      "totalNumberOfFiles" : 1,
      "totalFilesSize" : "77 B",
      "indexingSpeed" : "644 B/s",
      "biggestContributors" : [ {
        "providerName" : "Module 'Demo'",
        "numberOfFiles" : 1,
        "totalFilesSize" : "77 B",
        "partOfTotalIndexingTimeOfThisFileType" : "100.0%"
      } ]
    }, {
      "fileType" : "XHTML",
      "partOfTotalIndexingTime" : "< 1%",
      "partOfTotalContentLoadingTime" : "< 1%",
      "totalNumberOfFiles" : 1,
      "totalFilesSize" : "2.91 kB",
      "indexingSpeed" : "220.09 kB/s",
      "biggestContributors" : [ {
        "providerName" : "com.intellij.javaee.ExternalResourcesRootsProvider@4ec914be",
        "numberOfFiles" : 1,
        "totalFilesSize" : "2.91 kB",
        "partOfTotalIndexingTimeOfThisFileType" : "100.0%"
      } ]
    }, {
      "fileType" : "Shell Script",
      "partOfTotalIndexingTime" : "< 1%",
      "partOfTotalContentLoadingTime" : "< 1%",
      "totalNumberOfFiles" : 1,
      "totalFilesSize" : "1.48 kB",
      "indexingSpeed" : "167.38 kB/s",
      "biggestContributors" : [ {
        "providerName" : "com.intellij.javaee.ExternalResourcesRootsProvider@4ec914be",
        "numberOfFiles" : 1,
        "totalFilesSize" : "1.48 kB",
        "partOfTotalIndexingTimeOfThisFileType" : "100.0%"
      } ]
    }, {
      "fileType" : "textmate",
      "partOfTotalIndexingTime" : "< 1%",
      "partOfTotalContentLoadingTime" : "< 1%",
      "totalNumberOfFiles" : 2,
      "totalFilesSize" : "1.57 kB",
      "indexingSpeed" : "305.88 kB/s",
      "biggestContributors" : [ {
        "providerName" : "com.intellij.javaee.ExternalResourcesRootsProvider@4ec914be",
        "numberOfFiles" : 2,
        "totalFilesSize" : "1.57 kB",
        "partOfTotalIndexingTimeOfThisFileType" : "100.0%"
      } ]
    }, {
      "fileType" : "PLAIN_TEXT",
      "partOfTotalIndexingTime" : "< 1%",
      "partOfTotalContentLoadingTime" : "< 1%",
      "totalNumberOfFiles" : 2,
      "totalFilesSize" : "9.99 kB",
      "indexingSpeed" : "5.02 MB/s",
      "biggestContributors" : [ {
        "providerName" : "com.intellij.javaee.ExternalResourcesRootsProvider@4ec914be",
        "numberOfFiles" : 2,
        "totalFilesSize" : "9.99 kB",
        "partOfTotalIndexingTimeOfThisFileType" : "100.0%"
      } ]
    }, {
      "fileType" : "PATCH",
      "partOfTotalIndexingTime" : "< 1%",
      "partOfTotalContentLoadingTime" : "< 1%",
      "totalNumberOfFiles" : 8,
      "totalFilesSize" : "4.45 kB",
      "indexingSpeed" : "3.68 MB/s",
      "biggestContributors" : [ {
        "providerName" : "com.intellij.javaee.ExternalResourcesRootsProvider@4ec914be",
        "numberOfFiles" : 8,
        "totalFilesSize" : "4.45 kB",
        "partOfTotalIndexingTimeOfThisFileType" : "100.0%"
      } ]
    } ],
    "totalStatsPerIndexer" : [ {
      "indexId" : "IdIndex",
      "partOfTotalIndexingTime" : "40.1%",
      "totalNumberOfFiles" : 212,
      "totalNumberOfFilesIndexedByExtensions" : 0,
      "totalFilesSize" : "2.14 MB",
      "indexingSpeed" : "3.08 MB/s"
    }, {
      "indexId" : "Trigram.Index",
      "partOfTotalIndexingTime" : "26.6%",
      "totalNumberOfFiles" : 220,
      "totalNumberOfFilesIndexedByExtensions" : 0,
      "totalFilesSize" : "2.15 MB",
      "indexingSpeed" : "4.65 MB/s"
    }, {
      "indexId" : "XmlNamespaces",
      "partOfTotalIndexingTime" : "10.8%",
      "totalNumberOfFiles" : 18,
      "totalNumberOfFilesIndexedByExtensions" : 0,
      "totalFilesSize" : "866.44 kB",
      "indexingSpeed" : "4.6 MB/s"
    }, {
      "indexId" : "XmlTagNames",
      "partOfTotalIndexingTime" : "6.4%",
      "totalNumberOfFiles" : 11,
      "totalNumberOfFilesIndexedByExtensions" : 0,
      "totalFilesSize" : "415.21 kB",
      "indexingSpeed" : "3.75 MB/s"
    }, {
      "indexId" : "Stubs",
      "partOfTotalIndexingTime" : "5.6%",
      "totalNumberOfFiles" : 22,
      "totalNumberOfFilesIndexedByExtensions" : 0,
      "totalFilesSize" : "1.06 MB",
      "indexingSpeed" : "10.99 MB/s"
    }, {
      "indexId" : "SchemaTypeInheritance",
      "partOfTotalIndexingTime" : "3.7%",
      "totalNumberOfFiles" : 11,
      "totalNumberOfFilesIndexedByExtensions" : 0,
      "totalFilesSize" : "415.21 kB",
      "indexingSpeed" : "6.42 MB/s"
    }, {
      "indexId" : "TodoIndex",
      "partOfTotalIndexingTime" : "3.5%",
      "totalNumberOfFiles" : 1,
      "totalNumberOfFilesIndexedByExtensions" : 0,
      "totalFilesSize" : "77 B",
      "indexingSpeed" : "1.27 kB/s"
    }, {
      "indexId" : "java.null.method.argument",
      "partOfTotalIndexingTime" : "1.3%",
      "totalNumberOfFiles" : 1,
      "totalNumberOfFilesIndexedByExtensions" : 0,
      "totalFilesSize" : "77 B",
      "indexingSpeed" : "3.55 kB/s"
    }, {
      "indexId" : "DomFileIndex",
      "partOfTotalIndexingTime" : "< 1%",
      "totalNumberOfFiles" : 21,
      "totalNumberOfFilesIndexedByExtensions" : 0,
      "totalFilesSize" : "1.06 MB",
      "indexingSpeed" : "66.96 MB/s"
    }, {
      "indexId" : "xmlProperties",
      "partOfTotalIndexingTime" : "< 1%",
      "totalNumberOfFiles" : 1,
      "totalNumberOfFilesIndexedByExtensions" : 0,
      "totalFilesSize" : "168.37 kB",
      "indexingSpeed" : "13.01 MB/s"
    }, {
      "indexId" : "java.fun.expression",
      "partOfTotalIndexingTime" : "< 1%",
      "totalNumberOfFiles" : 1,
      "totalNumberOfFilesIndexedByExtensions" : 0,
      "totalFilesSize" : "77 B",
      "indexingSpeed" : "31.15 kB/s"
    }, {
      "indexId" : "IdeaPluginRegistrationIndex",
      "partOfTotalIndexingTime" : "< 1%",
      "totalNumberOfFiles" : 21,
      "totalNumberOfFilesIndexedByExtensions" : 0,
      "totalFilesSize" : "1.06 MB",
      "indexingSpeed" : "1.05 GB/s"
    }, {
      "indexId" : "java.binary.plus.expression",
      "partOfTotalIndexingTime" : "< 1%",
      "totalNumberOfFiles" : 1,
      "totalNumberOfFilesIndexedByExtensions" : 0,
      "totalFilesSize" : "77 B",
      "indexingSpeed" : "80.02 kB/s"
    }, {
      "indexId" : "PluginIdDependenciesIndex",
      "partOfTotalIndexingTime" : "< 1%",
      "totalNumberOfFiles" : 21,
      "totalNumberOfFilesIndexedByExtensions" : 0,
      "totalFilesSize" : "1.06 MB",
      "indexingSpeed" : "2.4 GB/s"
    }, {
      "indexId" : "devkit.ExtensionPointIndex",
      "partOfTotalIndexingTime" : "< 1%",
      "totalNumberOfFiles" : 21,
      "totalNumberOfFilesIndexedByExtensions" : 0,
      "totalFilesSize" : "1.06 MB",
      "indexingSpeed" : "3.06 GB/s"
    }, {
      "indexId" : "devkit.ExtensionPointClassIndex",
      "partOfTotalIndexingTime" : "< 1%",
      "totalNumberOfFiles" : 21,
      "totalNumberOfFilesIndexedByExtensions" : 0,
      "totalFilesSize" : "1.06 MB",
      "indexingSpeed" : "5.12 GB/s"
    }, {
      "indexId" : "PluginIdModuleIndex",
      "partOfTotalIndexingTime" : "< 1%",
      "totalNumberOfFiles" : 21,
      "totalNumberOfFilesIndexedByExtensions" : 0,
      "totalFilesSize" : "1.06 MB",
      "indexingSpeed" : "5.2 GB/s"
    } ],
    "fileProviderStatistics" : [ {
      "providerName" : "com.intellij.javaee.ExternalResourcesRootsProvider@4ec914be",
      "totalNumberOfFiles" : 219,
      "totalNumberOfFilesFullyIndexedByExtensions" : 0,
      "totalIndexingTime" : "663 ms",
      "statsPerFileType" : [ {
        "fileType" : "XML",
        "numberOfFiles" : 21,
        "totalFilesSize" : "1.06 MB",
        "partOfTotalIndexingTime" : "55.9%",
        "partOfTotalContentLoadingTime" : "76.9%"
      }, {
        "fileType" : "DTD",
        "numberOfFiles" : 62,
        "totalFilesSize" : "601.85 kB",
        "partOfTotalIndexingTime" : "29.9%",
        "partOfTotalContentLoadingTime" : "14.8%"
      }, {
        "fileType" : "RNG Compact",
        "numberOfFiles" : 122,
        "totalFilesSize" : "461.81 kB",
        "partOfTotalIndexingTime" : "12.3%",
        "partOfTotalContentLoadingTime" : "7.8%"
      }, {
        "fileType" : "XHTML",
        "numberOfFiles" : 1,
        "totalFilesSize" : "2.91 kB",
        "partOfTotalIndexingTime" : "< 1%",
        "partOfTotalContentLoadingTime" : "< 1%"
      }, {
        "fileType" : "Shell Script",
        "numberOfFiles" : 1,
        "totalFilesSize" : "1.48 kB",
        "partOfTotalIndexingTime" : "< 1%",
        "partOfTotalContentLoadingTime" : "< 1%"
      }, {
        "fileType" : "textmate",
        "numberOfFiles" : 2,
        "totalFilesSize" : "1.57 kB",
        "partOfTotalIndexingTime" : "< 1%",
        "partOfTotalContentLoadingTime" : "< 1%"
      }, {
        "fileType" : "PLAIN_TEXT",
        "numberOfFiles" : 2,
        "totalFilesSize" : "9.99 kB",
        "partOfTotalIndexingTime" : "< 1%",
        "partOfTotalContentLoadingTime" : "< 1%"
      }, {
        "fileType" : "PATCH",
        "numberOfFiles" : 8,
        "totalFilesSize" : "4.45 kB",
        "partOfTotalIndexingTime" : "< 1%",
        "partOfTotalContentLoadingTime" : "< 1%"
      } ],
      "statsPerIndexer" : [ {
        "indexId" : "IdIndex",
        "numberOfFiles" : 211,
        "numberOfFilesIndexedByExtensions" : 0,
        "partOfTotalIndexingTime" : "42.8%"
      }, {
        "indexId" : "Trigram.Index",
        "numberOfFiles" : 219,
        "numberOfFilesIndexedByExtensions" : 0,
        "partOfTotalIndexingTime" : "28.4%"
      }, {
        "indexId" : "XmlNamespaces",
        "numberOfFiles" : 18,
        "numberOfFilesIndexedByExtensions" : 0,
        "partOfTotalIndexingTime" : "11.7%"
      }, {
        "indexId" : "XmlTagNames",
        "numberOfFiles" : 11,
        "numberOfFilesIndexedByExtensions" : 0,
        "partOfTotalIndexingTime" : "6.9%"
      }, {
        "indexId" : "Stubs",
        "numberOfFiles" : 21,
        "numberOfFilesIndexedByExtensions" : 0,
        "partOfTotalIndexingTime" : "4.4%"
      }, {
        "indexId" : "SchemaTypeInheritance",
        "numberOfFiles" : 11,
        "numberOfFilesIndexedByExtensions" : 0,
        "partOfTotalIndexingTime" : "4.0%"
      } ],
      "fastIndexers" : [ "DomFileIndex", "IdeaPluginRegistrationIndex", "PluginIdDependenciesIndex", "PluginIdModuleIndex", "devkit.ExtensionPointClassIndex", "devkit.ExtensionPointIndex", "xmlProperties" ]
    }, {
      "providerName" : "Module 'Demo'",
      "totalNumberOfFiles" : 1,
      "totalNumberOfFilesFullyIndexedByExtensions" : 0,
      "totalIndexingTime" : "138 ms",
      "statsPerFileType" : [ {
        "fileType" : "JAVA",
        "numberOfFiles" : 1,
        "totalFilesSize" : "77 B",
        "partOfTotalIndexingTime" : "100.0%",
        "partOfTotalContentLoadingTime" : "100.0%"
      } ],
      "statsPerIndexer" : [ {
        "indexId" : "TodoIndex",
        "numberOfFiles" : 1,
        "numberOfFilesIndexedByExtensions" : 0,
        "partOfTotalIndexingTime" : "50.8%"
      }, {
        "indexId" : "Stubs",
        "numberOfFiles" : 1,
        "numberOfFilesIndexedByExtensions" : 0,
        "partOfTotalIndexingTime" : "21.9%"
      }, {
        "indexId" : "java.null.method.argument",
        "numberOfFiles" : 1,
        "numberOfFilesIndexedByExtensions" : 0,
        "partOfTotalIndexingTime" : "18.2%"
      }, {
        "indexId" : "IdIndex",
        "numberOfFiles" : 1,
        "numberOfFilesIndexedByExtensions" : 0,
        "partOfTotalIndexingTime" : "4.6%"
      }, {
        "indexId" : "java.fun.expression",
        "numberOfFiles" : 1,
        "numberOfFilesIndexedByExtensions" : 0,
        "partOfTotalIndexingTime" : "2.1%"
      }, {
        "indexId" : "Trigram.Index",
        "numberOfFiles" : 1,
        "numberOfFilesIndexedByExtensions" : 0,
        "partOfTotalIndexingTime" : "1.7%"
      } ],
      "fastIndexers" : [ "java.binary.plus.expression" ]
    } ]
  }
}